okserve/__init__.py
okserve-0.1.1.dist-info/LICENSE
okserve-0.1.1.dist-info/METADATA
okserve-0.1.1.dist-info/WHEEL
okserve-0.1.1.dist-info/RECORD
